grokcore.view-4.1-py3.12-nspkg.pth
grokcore/view/__init__.py
grokcore/view/components.py
grokcore/view/configure.zcml
grokcore/view/directive.py
grokcore/view/ftesting.zcml
grokcore/view/interfaces.py
grokcore/view/meta-minimal.zcml
grokcore/view/meta.zcml
grokcore/view/publication.py
grokcore/view/publication_security.zcml
grokcore/view/templatereg.py
grokcore/view/templatereg.txt
grokcore/view/testing.py
grokcore/view/util.py
grokcore/view/zcml.py
grokcore/view/meta/__init__.py
grokcore/view/meta/contentproviders.py
grokcore/view/meta/directoryresource.py
grokcore/view/meta/skin.py
grokcore/view/meta/templates.py
grokcore/view/meta/views.py
grokcore/view/tests/__init__.py
grokcore/view/tests/test_base.py
grokcore/view/tests/test_functional.py
grokcore/view/tests/base/__init__.py
grokcore/view/tests/base/contentprovider/__init__.py
grokcore/view/tests/base/contentprovider/contentprovider_references.py
grokcore/view/tests/base/contentprovider/contentprovider_render_and_template.py
grokcore/view/tests/base/contentprovider/render_and_template_templates/contentprovider.pt
grokcore/view/tests/base/directoryresource/__init__.py
grokcore/view/tests/base/directoryresource/directoryispackage.py
grokcore/view/tests/base/directoryresource/directoryresources.py
grokcore/view/tests/base/directoryresource/directoryispackage_fixture/__init__.py
grokcore/view/tests/base/directoryresource/directoryispackage_fixture/resource.py
grokcore/view/tests/base/directoryresource/directoryispackage_fixture/foo/__init__.py
grokcore/view/tests/base/directoryresource/directoryresources_fixture/__init__.py
grokcore/view/tests/base/directoryresource/directoryresources_fixture/resource.py
grokcore/view/tests/base/directoryresource/directoryresources_fixture/bar/baz/resourceinbaz.txt
grokcore/view/tests/base/directoryresource/directoryresources_fixture/foo/resourceinfoo.txt
grokcore/view/tests/base/skin/__init__.py
grokcore/view/tests/base/skin/conflict.py
grokcore/view/tests/base/skin/directive.py
grokcore_view-4.1.dist-info/licenses/LICENSE.txt
grokcore_view-4.1.dist-info/METADATA
grokcore_view-4.1.dist-info/WHEEL
grokcore_view-4.1.dist-info/namespace_packages.txt
grokcore_view-4.1.dist-info/top_level.txt
grokcore_view-4.1.dist-info/RECORD
