Metadata-Version: 2.4
Name: grokcore.view
Version: 4.1
Summary: Grok-like configuration for Zope browser pages
Home-page: https://github.com/zopefoundation/grokcore.view
Download-URL: https://pypi.org/project/grokcore.view/
Author: Grok Team
Author-email: zope-dev@zope.dev
License: ZPL
Classifier: Development Status :: 6 - Mature
Classifier: Environment :: Web Environment
Classifier: Framework :: Zope :: 3
Classifier: Intended Audience :: Developers
Classifier: License :: OSI Approved :: Zope Public License
Classifier: Programming Language :: Python
Classifier: Programming Language :: Python :: 3
Classifier: Programming Language :: Python :: 3.9
Classifier: Programming Language :: Python :: 3.10
Classifier: Programming Language :: Python :: 3.11
Classifier: Programming Language :: Python :: 3.12
Classifier: Programming Language :: Python :: 3.13
Classifier: Programming Language :: Python :: Implementation
Classifier: Programming Language :: Python :: Implementation :: CPython
Classifier: Programming Language :: Python :: Implementation :: PyPy
Requires-Python: >=3.9
License-File: LICENSE.txt
Requires-Dist: grokcore.component>=2.5
Requires-Dist: grokcore.security
Requires-Dist: martian>=1.5
Requires-Dist: setuptools
Requires-Dist: zope.browserpage
Requires-Dist: zope.browserresource>=3.9
Requires-Dist: zope.component
Requires-Dist: zope.contentprovider
Requires-Dist: zope.interface
Requires-Dist: zope.pagetemplate
Requires-Dist: zope.ptresource>=3.9
Requires-Dist: zope.publisher
Requires-Dist: zope.security
Requires-Dist: zope.traversing
Provides-Extra: test
Requires-Dist: zope.app.appsetup; extra == "test"
Requires-Dist: zope.app.publication; extra == "test"
Requires-Dist: zope.app.wsgi[test]; extra == "test"
Requires-Dist: zope.configuration; extra == "test"
Requires-Dist: zope.container; extra == "test"
Requires-Dist: zope.login; extra == "test"
Requires-Dist: zope.password; extra == "test"
Requires-Dist: zope.principalregistry; extra == "test"
Requires-Dist: zope.securitypolicy; extra == "test"
Requires-Dist: zope.site; extra == "test"
Requires-Dist: zope.testbrowser; extra == "test"
Requires-Dist: zope.testing; extra == "test"
Provides-Extra: security-publication
Requires-Dist: zope.app.publication; extra == "security-publication"
Dynamic: author
Dynamic: author-email
Dynamic: classifier
Dynamic: description
Dynamic: download-url
Dynamic: home-page
Dynamic: license
Dynamic: license-file
Dynamic: provides-extra
Dynamic: requires-dist
Dynamic: requires-python
Dynamic: summary
